{
  "title": "Kapitola 10 – Přiznání – Kdo je kdo",
  "sections": [
    {
      "id": "10.1",
      "title": "Pravěk",
      "content": "Podle mnohých dnešních vědců začíná život lidí v pravěku, ale pravěk vznikne vždy po konci vyspělé civilizace...\n(...)"
    },
    {
      "id": "10.2",
      "title": "Buddha",
      "content": "Přeskočíme pár tisíc let a několik menších restartů, protože jinak by kniha nikdy neskončila...\n(...)"
    },
    {
      "id": "10.3",
      "title": "Platon",
      "content": "Jako například Platon jsem velmi často debatoval s přítelem Sokratem...\n(...)"
    }
  ]
}